README.md
setup.py
Topsis_Kashish_102117150.egg-info/PKG-INFO
Topsis_Kashish_102117150.egg-info/SOURCES.txt
Topsis_Kashish_102117150.egg-info/dependency_links.txt
Topsis_Kashish_102117150.egg-info/requires.txt
Topsis_Kashish_102117150.egg-info/top_level.txt
topsis_Kashish_102117150/__init__.py
topsis_Kashish_102117150/__main__.py