Metadata-Version: 2.1
Name: Topsis-Kashish-102117150
Version: 1.0
Summary: A package for performing TOPSIS analysis
Author: Kashish
Author-email: <kkashish_be21@thapar.edu>
Keywords: python,topsis
Classifier: Programming Language :: Python :: 3
Classifier: License :: OSI Approved :: MIT License
Classifier: Operating System :: OS Independent
Requires-Dist: python
Requires-Dist: numpy
Requires-Dist: pandas
Requires-Dist: sys
